MANIFEST.in
README.rst
manage.py
setup.py
job_runner/__init__.py
job_runner/urls.py
job_runner/wsgi.py
job_runner.egg-info/PKG-INFO
job_runner.egg-info/SOURCES.txt
job_runner.egg-info/dependency_links.txt
job_runner.egg-info/requires.txt
job_runner.egg-info/top_level.txt
job_runner/apps/__init__.py
job_runner/apps/job_runner/__init__.py
job_runner/apps/job_runner/admin.py
job_runner/apps/job_runner/api.py
job_runner/apps/job_runner/api_urls.py
job_runner/apps/job_runner/auth.py
job_runner/apps/job_runner/managers.py
job_runner/apps/job_runner/models.py
job_runner/apps/job_runner/notifications.py
job_runner/apps/job_runner/signals.py
job_runner/apps/job_runner/urls.py
job_runner/apps/job_runner/utils.py
job_runner/apps/job_runner/views.py
job_runner/apps/job_runner/fixtures/test_auth.json
job_runner/apps/job_runner/fixtures/test_child_job.json
job_runner/apps/job_runner/fixtures/test_job_templates.json
job_runner/apps/job_runner/fixtures/test_jobs.json
job_runner/apps/job_runner/fixtures/test_projects.json
job_runner/apps/job_runner/fixtures/test_worker_pools.json
job_runner/apps/job_runner/fixtures/test_workers.json
job_runner/apps/job_runner/management/__init__.py
job_runner/apps/job_runner/management/commands/__init__.py
job_runner/apps/job_runner/management/commands/broadcast_queue.py
job_runner/apps/job_runner/management/commands/health_check.py
job_runner/apps/job_runner/migrations/0001_initial.py
job_runner/apps/job_runner/migrations/0002_auto__add_field_job_enqueue_is_enabled__add_field_run_is_manual.py
job_runner/apps/job_runner/migrations/0003_auto__add_field_run_schedule_children.py
job_runner/apps/job_runner/migrations/0004_auto__add_unique_job_job_template_title.py
job_runner/apps/job_runner/migrations/0005_auto__add_field_rescheduleexclude_note__add_field_worker_description__.py
job_runner/apps/job_runner/migrations/0006_auto.py
job_runner/apps/job_runner/migrations/0007_auto__add_field_worker_enqueue_is_enabled__add_field_project_enqueue_i.py
job_runner/apps/job_runner/migrations/0008_auto__add_field_job_fail_times__add_field_job_disable_enqueue_after_fa.py
