Metadata-Version: 1.0
Name: job-runner
Version: 3.5.2
Summary: Tool for scheduling jobs and realtime monitoring
Home-page: http://github.com/spilgames/job-runner
Author: Spil Games
Author-email: datawarehouse@spilgames.com
License: BSD
Platform: UNKNOWN
